octave_mcp/__init__.py
octave_mcp/py.typed
octave_mcp/cli/__init__.py
octave_mcp/cli/main.py
octave_mcp/core/__init__.py
octave_mcp/core/ast_nodes.py
octave_mcp/core/constraints.py
octave_mcp/core/coverage_mapper.py
octave_mcp/core/emitter.py
octave_mcp/core/file_ops.py
octave_mcp/core/gbnf_compiler.py
octave_mcp/core/grammar.py
octave_mcp/core/holographic.py
octave_mcp/core/hydrator.py
octave_mcp/core/lexer.py
octave_mcp/core/parser.py
octave_mcp/core/projector.py
octave_mcp/core/repair.py
octave_mcp/core/repair_log.py
octave_mcp/core/routing.py
octave_mcp/core/schema.py
octave_mcp/core/schema_extractor.py
octave_mcp/core/sealer.py
octave_mcp/core/validator.py
octave_mcp/integrations/__init__.py
octave_mcp/integrations/llama_cpp.py
octave_mcp/integrations/outlines.py
octave_mcp/integrations/vllm.py
octave_mcp/mcp/__init__.py
octave_mcp/mcp/base_tool.py
octave_mcp/mcp/eject.py
octave_mcp/mcp/server.py
octave_mcp/mcp/validate.py
octave_mcp/mcp/write.py
octave_mcp/resources/README.md
octave_mcp/resources/__init__.py
octave_mcp/resources/primers/octave-compression-primer.oct.md
octave_mcp/resources/primers/octave-literacy-primer.oct.md
octave_mcp/resources/primers/octave-mastery-primer.oct.md
octave_mcp/resources/primers/octave-mythology-primer.oct.md
octave_mcp/resources/primers/octave-ultra-mythic-primer.oct.md
octave_mcp/resources/skills/octave-compression/SKILL.md
octave_mcp/resources/skills/octave-literacy/SKILL.md
octave_mcp/resources/skills/octave-mastery/SKILL.md
octave_mcp/resources/skills/octave-mythology/SKILL.md
octave_mcp/resources/skills/octave-ultra-mythic/SKILL.md
octave_mcp/resources/specs/SPEC_TEMPLATE.oct.md
octave_mcp/resources/specs/__init__.py
octave_mcp/resources/specs/octave-agents-spec.oct.md
octave_mcp/resources/specs/octave-core-spec.oct.md
octave_mcp/resources/specs/octave-data-spec.oct.md
octave_mcp/resources/specs/octave-execution-spec.oct.md
octave_mcp/resources/specs/octave-mcp-architecture.oct.md
octave_mcp-1.0.0.dist-info/licenses/LICENSE
octave_mcp-1.0.0.dist-info/METADATA
octave_mcp-1.0.0.dist-info/WHEEL
octave_mcp-1.0.0.dist-info/entry_points.txt
octave_mcp-1.0.0.dist-info/top_level.txt
octave_mcp-1.0.0.dist-info/RECORD
