Metadata-Version: 2.4
Name: octave-mcp
Version: 1.0.0
Summary: OCTAVE MCP Server - Lenient-to-Canonical OCTAVE pipeline with schema validation and generative holographic contracts
Author-email: Elevana <shaun.buswell@elevana.com>
Maintainer-email: Elevana <shaun.buswell@elevana.com>
License: Apache-2.0
Project-URL: Homepage, https://github.com/elevanaltd/octave-mcp
Project-URL: Documentation, https://github.com/elevanaltd/octave-mcp/tree/main/docs
Project-URL: Repository, https://github.com/elevanaltd/octave-mcp.git
Project-URL: Issues, https://github.com/elevanaltd/octave-mcp/issues
Project-URL: Changelog, https://github.com/elevanaltd/octave-mcp/blob/main/CHANGELOG.md
Keywords: octave,mcp,model-context-protocol,ai,llm,protocol,schema-validation,compression
Classifier: Development Status :: 5 - Production/Stable
Classifier: Intended Audience :: Developers
Classifier: License :: OSI Approved :: Apache Software License
Classifier: Operating System :: OS Independent
Classifier: Programming Language :: Python :: 3
Classifier: Programming Language :: Python :: 3.11
Classifier: Programming Language :: Python :: 3.12
Classifier: Programming Language :: Python :: 3.13
Classifier: Topic :: Software Development :: Libraries :: Python Modules
Classifier: Topic :: Scientific/Engineering :: Artificial Intelligence
Classifier: Typing :: Typed
Requires-Python: >=3.11
License-File: LICENSE
Requires-Dist: mcp>=1.0.0
Requires-Dist: click>=8.0.0
Requires-Dist: pydantic>=2.0.0
Requires-Dist: python-dotenv>=1.0.0
Requires-Dist: PyYAML>=6.0.0
Provides-Extra: dev
Requires-Dist: pytest>=7.0.0; extra == "dev"
Requires-Dist: pytest-cov>=4.0.0; extra == "dev"
Requires-Dist: pytest-asyncio>=0.21.0; extra == "dev"
Requires-Dist: pytest-timeout>=2.0.0; extra == "dev"
Requires-Dist: mypy>=1.0.0; extra == "dev"
Requires-Dist: types-PyYAML>=6.0.0; extra == "dev"
Requires-Dist: ruff>=0.1.0; extra == "dev"
Requires-Dist: black>=23.0.0; extra == "dev"
Requires-Dist: hypothesis>=6.0.0; extra == "dev"
Requires-Dist: pre-commit>=3.0.0; extra == "dev"
Dynamic: license-file
